glimix_core/__init__.py
glimix_core/_testit.py
glimix_core/_ep/__init__.py
glimix_core/_ep/ep.py
glimix_core/_ep/linear_kernel.py
glimix_core/_ep/posterior.py
glimix_core/_ep/posterior_linear_kernel.py
glimix_core/_ep/site.py
glimix_core/_util/__init__.py
glimix_core/_util/_array.py
glimix_core/_util/_assert.py
glimix_core/_util/_numbers.py
glimix_core/_util/_svd.py
glimix_core/_util/cache.py
glimix_core/_util/cached_property.py
glimix_core/_util/check.py
glimix_core/_util/eigen.py
glimix_core/_util/format.py
glimix_core/_util/random.py
glimix_core/_util/solve.py
glimix_core/_util/test/__init__.py
glimix_core/_util/test/test_util.py
glimix_core/cov/__init__.py
glimix_core/cov/_eye.py
glimix_core/cov/_free.py
glimix_core/cov/_given.py
glimix_core/cov/_kron2sum.py
glimix_core/cov/_linear.py
glimix_core/cov/_lrfree.py
glimix_core/cov/_sum.py
glimix_core/cov/test/__init__.py
glimix_core/cov/test/test_cov_eye.py
glimix_core/cov/test/test_cov_free.py
glimix_core/cov/test/test_cov_given.py
glimix_core/cov/test/test_cov_kron2sum.py
glimix_core/cov/test/test_cov_linear.py
glimix_core/cov/test/test_cov_lrfree.py
glimix_core/cov/test/test_cov_sum.py
glimix_core/example/__init__.py
glimix_core/ggp/__init__.py
glimix_core/ggp/_expfam.py
glimix_core/ggp/test/__init__.py
glimix_core/ggp/test/test_ggp_expfam.py
glimix_core/glmm/__init__.py
glimix_core/glmm/_expfam.py
glimix_core/glmm/_glmm.py
glimix_core/glmm/_normal.py
glimix_core/glmm/test/__init__.py
glimix_core/glmm/test/test_glmm_expfam.py
glimix_core/glmm/test/test_glmm_normal.py
glimix_core/gp/__init__.py
glimix_core/gp/_gp.py
glimix_core/gp/test/__init__.py
glimix_core/gp/test/test_gp.py
glimix_core/lik/__init__.py
glimix_core/lik/_prod.py
glimix_core/lik/test/__init__.py
glimix_core/lik/test/test_lik.py
glimix_core/link/__init__.py
glimix_core/link/_link.py
glimix_core/link/test/__init__.py
glimix_core/link/test/test_link.py
glimix_core/lmm/__init__.py
glimix_core/lmm/_b.py
glimix_core/lmm/_kron2sum.py
glimix_core-3.1.14.dist-info/METADATA
glimix_core-3.1.14.dist-info/WHEEL
glimix_core-3.1.14.dist-info/licenses/LICENSE.md
glimix_core-3.1.14.dist-info/RECORD
