Metadata-Version: 2.4
Name: glimix-core
Version: 3.1.14
Summary: Fast inference over mean and covariance parameters for Generalised Linear Mixed Models
Project-URL: Homepage, https://github.com/limix/glimix-core
Project-URL: Repository, https://github.com/limix/glimix-core
Author-email: Danilo Horta <danilo.horta@pm.me>
License-Expression: MIT
License-File: LICENSE.md
Keywords: glmm,lmm
Classifier: License :: OSI Approved :: MIT License
Requires-Python: ~=3.10
Requires-Dist: brent-search<3,>=2.0.2
Requires-Dist: liknorm<3,>=2.0.0
Requires-Dist: ndarray-listener<3,>=2.0.2
Requires-Dist: numpy-sugar<2,>=1.5.5
Requires-Dist: numpy~=2.1
Requires-Dist: optimix<4,>=3.0.6
Requires-Dist: scipy<2,>=1.15.0
Requires-Dist: tqdm<5,>=4.67.1
